thinkgreen/__init__.py
thinkgreen/thinkgreen.py
thinkgreen-0.0.3.dist-info/LICENSE
thinkgreen-0.0.3.dist-info/METADATA
thinkgreen-0.0.3.dist-info/WHEEL
thinkgreen-0.0.3.dist-info/dependency_links.txt
thinkgreen-0.0.3.dist-info/top_level.txt
thinkgreen-0.0.3.dist-info/RECORD
