Metadata-Version: 2.1
Name: thinkgreen
Version: 0.0.3
Summary: python package final project
Home-page: https://github.com/olilamm/thinkgreen
Author: Olivia Lamm
Author-email: olamm@vols.utk.edu
License: MIT license
Keywords: thinkgreen
Classifier: Development Status :: 2 - Pre-Alpha
Classifier: Intended Audience :: Developers
Classifier: License :: OSI Approved :: MIT License
Classifier: Natural Language :: English
Classifier: Programming Language :: Python :: 3
Classifier: Programming Language :: Python :: 3.7
Classifier: Programming Language :: Python :: 3.8
Classifier: Programming Language :: Python :: 3.9
Classifier: Programming Language :: Python :: 3.10
Requires-Python: >=3.7
License-File: LICENSE
Requires-Dist: folium
Requires-Dist: ipyleaflet
Requires-Dist: geopandas
